LICENSE
README.md
slackdump/__init__.py
slackdump/chrome.py
slackdump/scraper.py
slackdump-0.0.5.dist-info/entry_points.txt
slackdump-0.0.5.dist-info/LICENSE
slackdump-0.0.5.dist-info/WHEEL
slackdump-0.0.5.dist-info/METADATA
slackdump-0.0.5.dist-info/RECORD
