Metadata-Version: 2.1
Name: slackdump
Version: 0.0.5
Summary: dump slack data
Home-page: https://github.com/sloev/slackdump
License: MIT
Author: sloev
Author-email: johanned.valbjorn@gmail.com
Requires-Python: >=3.7,<4.0
Classifier: License :: OSI Approved :: MIT License
Classifier: Programming Language :: Python :: 3
Classifier: Programming Language :: Python :: 3.7
Classifier: Programming Language :: Python :: 3.8
Requires-Dist: pyppeteer (>=0.0.25,<0.0.26)
Project-URL: Repository, https://github.com/sloev/slackdump
